jupyterlite_xeus_python/__init__.py
jupyterlite_xeus_python/_version.py
jupyterlite_xeus_python/build.py
jupyterlite_xeus_python/env_build_addon.py
jupyterlite_xeus_python-1.0.0.data/data/share/jupyter/labextensions/@jupyterlite/xeus-python-kernel/package.json
jupyterlite_xeus_python-1.0.0.data/data/share/jupyter/labextensions/@jupyterlite/xeus-python-kernel/static/20.77d186eda9db5c9e8399.js
jupyterlite_xeus_python-1.0.0.data/data/share/jupyter/labextensions/@jupyterlite/xeus-python-kernel/static/213.efd3bb893df42f78e3eb.js
jupyterlite_xeus_python-1.0.0.data/data/share/jupyter/labextensions/@jupyterlite/xeus-python-kernel/static/213.efd3bb893df42f78e3eb.js.LICENSE.txt
jupyterlite_xeus_python-1.0.0.data/data/share/jupyter/labextensions/@jupyterlite/xeus-python-kernel/static/2e686ba7cfb8ce81b121cfe70372694a.png
jupyterlite_xeus_python-1.0.0.data/data/share/jupyter/labextensions/@jupyterlite/xeus-python-kernel/static/6e85a7c13b8c7a885d066fa507efaf32.png
jupyterlite_xeus_python-1.0.0.data/data/share/jupyter/labextensions/@jupyterlite/xeus-python-kernel/static/747.8acd39eb4f33f676e343.js
jupyterlite_xeus_python-1.0.0.data/data/share/jupyter/labextensions/@jupyterlite/xeus-python-kernel/static/870.d4e887a451fc3a0542ef.js
jupyterlite_xeus_python-1.0.0.data/data/share/jupyter/labextensions/@jupyterlite/xeus-python-kernel/static/870.d4e887a451fc3a0542ef.js.LICENSE.txt
jupyterlite_xeus_python-1.0.0.data/data/share/jupyter/labextensions/@jupyterlite/xeus-python-kernel/static/asttokens-2.4.1-pyhd8ed1ab_0.tar.gz
jupyterlite_xeus_python-1.0.0.data/data/share/jupyter/labextensions/@jupyterlite/xeus-python-kernel/static/backcall-0.2.0-pyh9f0ad1d_0.tar.gz
jupyterlite_xeus_python-1.0.0.data/data/share/jupyter/labextensions/@jupyterlite/xeus-python-kernel/static/decorator-5.1.1-pyhd8ed1ab_0.tar.gz
jupyterlite_xeus_python-1.0.0.data/data/share/jupyter/labextensions/@jupyterlite/xeus-python-kernel/static/empack_env_meta.json
jupyterlite_xeus_python-1.0.0.dist-info/METADATA
jupyterlite_xeus_python-1.0.0.dist-info/WHEEL
jupyterlite_xeus_python-1.0.0.dist-info/entry_points.txt
jupyterlite_xeus_python-1.0.0.dist-info/licenses/LICENSE
jupyterlite_xeus_python-1.0.0.dist-info/RECORD
