Metadata-Version: 2.1
Name: jupyterlite-xeus-python
Version: 1.0.0
Summary: A Python kernel for JupyterLite, powered by Xeus
Project-URL: Homepage, https://github.com/jupyterlite/xeus-python-kernel
Project-URL: Bug Tracker, https://github.com/jupyterlite/xeus-python-kernel/issues
Project-URL: Repository, https://github.com/jupyterlite/xeus-python-kernel.git
Author: JupyterLite Contributors
License: BSD 3-Clause License
License-File: LICENSE
Classifier: Framework :: Jupyter
Classifier: Framework :: Jupyter :: JupyterLab
Classifier: Framework :: Jupyter :: JupyterLab :: 4
Classifier: Framework :: Jupyter :: JupyterLab :: Extensions
Classifier: Framework :: Jupyter :: JupyterLab :: Extensions :: Prebuilt
Classifier: License :: OSI Approved :: BSD License
Classifier: Programming Language :: Python
Classifier: Programming Language :: Python :: 3
Classifier: Programming Language :: Python :: 3.8
Classifier: Programming Language :: Python :: 3.9
Classifier: Programming Language :: Python :: 3.10
Classifier: Programming Language :: Python :: 3.11
Requires-Python: >=3.8
Requires-Dist: empack<4,>=3.1
Requires-Dist: jupyterlite-core<0.3,>=0.2.0rc0
Requires-Dist: requests
Requires-Dist: traitlets
Requires-Dist: typer
Provides-Extra: dev
Requires-Dist: black; extra == 'dev'
Requires-Dist: ruff==0.0.292; extra == 'dev'
